rpsl_lexer/__init__.py
rpsl_lexer/afi.py
rpsl_lexer/aut_num.py
rpsl_lexer/filter_set.py
rpsl_lexer/lex.py
rpsl_lexer/lines.py
rpsl_lexer/parse.py
rpsl_lexer/peering_set.py
rpsl_lexer/piped.py
rpsl_lexer/rpsl_object.py
rpsl_lexer-0.3.1.dist-info/METADATA
rpsl_lexer-0.3.1.dist-info/WHEEL
rpsl_lexer-0.3.1.dist-info/RECORD
