Metadata-Version: 2.3
Name: rpsl-lexer
Version: 0.3.1
Summary: RPSL lexer for Internet Route Verification.
Project-URL: repository, https://github.com/SichangHe/internet_route_verification
Author-email: "Steven Hé (Sīchàng)" <stevensichanghe@gmail.com>
Requires-Python: >=3.10
Requires-Dist: pyparsing>=3.1.2
